rossmann_toolbox/__init__.py
rossmann_toolbox/models/__init__.py
rossmann_toolbox/models/edge_gat_layer.py
rossmann_toolbox/models/seqcoredetect.py
rossmann_toolbox/models/seqcoreeval.py
rossmann_toolbox/models/structmodel.py
rossmann_toolbox/models/structwrapper.py
rossmann_toolbox/rtb.py
rossmann_toolbox/utils/__init__.py
rossmann_toolbox/utils/bio_params.py
rossmann_toolbox/utils/dssp.py
rossmann_toolbox/utils/encoders.py
rossmann_toolbox/utils/foldx_parser.py
rossmann_toolbox/utils/generators.py
rossmann_toolbox/utils/graph_feat_prep.py
rossmann_toolbox/utils/graph_loader_opt.py
rossmann_toolbox/utils/hhdb/core_a3m.ffdata
rossmann_toolbox/utils/hhdb/core_a3m.ffindex
rossmann_toolbox/utils/hhdb/core_cs219.ffdata
rossmann_toolbox/utils/hhdb/core_cs219.ffindex
rossmann_toolbox/utils/hhdb/core_hhm.ffdata
rossmann_toolbox/utils/hhdb/core_hhm.ffindex
rossmann_toolbox/utils/myfoldx.py
rossmann_toolbox/utils/seqvec.py
rossmann_toolbox/utils/solveX.py
rossmann_toolbox/utils/struct_loader.py
rossmann_toolbox/utils/struct_model_hparams.py
rossmann_toolbox/utils/tools.py
rossmann_toolbox/utils/utils.py
rossmann_toolbox/weights/0.pt
rossmann_toolbox/weights/1.pt
rossmann_toolbox/weights/2.pt
rossmann_toolbox/weights/3.pt
rossmann_toolbox/weights/4.pt
rossmann_toolbox/weights/coredetector.pt
rossmann_toolbox/weights/seqvec/uniref50_v2/options.json
rossmann_toolbox/weights/struct_ensemble/hp1.ckpt
rossmann_toolbox/weights/struct_ensemble/hp2.ckpt
rossmann_toolbox/weights/struct_ensemble/hp3.ckpt
rossmann_toolbox/weights/struct_ensemble/hp4.ckpt
rossmann_toolbox/weights/struct_ensemble/model1.ckpt
rossmann_toolbox/weights/struct_ensemble/model2.ckpt
rossmann_toolbox/weights/struct_ensemble/model3.ckpt
rossmann_toolbox/weights/struct_ensemble/model4.ckpt
rossmann_toolbox/weights/struct_ensemble/scaler.pkl.gz
rossmann_toolbox-0.1.1.dist-info/LICENSE
rossmann_toolbox-0.1.1.dist-info/WHEEL
rossmann_toolbox-0.1.1.dist-info/METADATA
rossmann_toolbox-0.1.1.dist-info/RECORD
