Metadata-Version: 2.1
Name: rossmann-toolbox
Version: 0.1.1
Summary: Prediction and re-engineering of the cofactor specificity of Rossmann-fold proteins
Home-page: https://github.com/labstructbioinf/rossmann-toolbox
License: MIT
Author: Kamil Kaminski
Author-email: k.kaminski@cent.uw.edu.pl
Requires-Python: >=3.7,<4.0
Classifier: Intended Audience :: Science/Research
Classifier: License :: OSI Approved :: MIT License
Classifier: Programming Language :: Python :: 3
Classifier: Programming Language :: Python :: 3.7
Classifier: Programming Language :: Python :: 3.8
Classifier: Programming Language :: Python :: 3.9
Classifier: Programming Language :: Python :: 3.10
Classifier: Programming Language :: Python :: 3.11
Classifier: Programming Language :: Python :: 3 :: Only
Classifier: Topic :: Scientific/Engineering :: Artificial Intelligence
Classifier: Topic :: Scientific/Engineering :: Bio-Informatics
Requires-Dist: aiohttp (>=3.7.4,<4.0.0)
Requires-Dist: atomium (==1.0.9)
Requires-Dist: biopython (==1.78)
Requires-Dist: captum (==0.3.1)
Requires-Dist: conditional (>=1.3,<2.0)
Requires-Dist: csb (>=1.2.5,<2.0.0)
Requires-Dist: dgl (==0.6.1)
Requires-Dist: greenlet (<1)
Requires-Dist: overrides (>=3.0,<4.0)
Requires-Dist: pandas (==1.1.5)
Requires-Dist: seqvec (==0.4.1)
Requires-Dist: torch (>=1.13,<2.0)
Project-URL: Repository, https://github.com/labstructbioinf/rossmann-toolbox
